Labs/Lab1/GCD/GCD.sv
`timescale 1ns/1ps 

module GCD (
input  logic clk,  
input  logic rst_n,
input  logic [31:0] a_in,
input  logic [31:0] b_in,
output logic done,
output logic [31:0] gcd
);

parameter s0 = 2'd0, s1 = 2'd1, s2 = 2'd2, s3=2'd3;

logic [1:0] state;
logic [1:0] state_next;
logic [31:0] a_next, a;
logic [31:0] b_next, b;

always @(posedge clk) begin
  if(rst_n) begin
    a      <= 0;    
    b      <= 0;
    state  <= s0;
  end else begin
    a <= a_next;
    b <= b_next;
    state <= state_next;
  end
end

always @(*) begin
    a_next = a;
    b_next = b;
    gcd    = 32'd0;   
    state_next = state;
    case (state)
      s0: begin
            a_next      = a_in;
            b_next      = b_in;
            gcd         = 32'd0;
            state_next  = s1; 
            done        = 0;
        end
      s1: begin
        if(a!=b) begin
            a_next= (a >= b) ? a - b : a;
            b_next     = (b >  a) ? b - a : b;
            gcd        = 32'd0;
            state_next = s1;
        end else begin
            state_next = s2;
            end
        end
      s2: begin
            gcd = a;
            state_next = s0;
            done = 1;
        end
        default: begin
            state_next = s0;
        end
    endcase
end
endmodule

Labs/Lab1/GCD/GCDTest.sv
`timescale 1ns/1ps 

module GCDTest;
logic clk, rst, done;
logic [31:0] a,b,gcd;

GCD gcd_inst(.clk(clk),.rst_n(rst),.a_in(a), .b_in(b), .done(done), .gcd(gcd));

initial begin 
    clk = 0;
    forever begin
      #50ns clk = !clk;
    end
end


function int gcd_fcn(int a, int b);
    return b == 0 ? a : gcd_fcn(b, a % b);
endfunction

function int gcd_fcn_while(int a, int b);
  while(a!=b) begin
      if(a>b) a = a-b;
      else    b = b-a;       
  end
  return a;
endfunction : gcd_fcn_while

initial begin
  int NUM_TESTS = 1000;
  int expected_val = 0;
  int test_id = 0;
  rst=1; 
  a = 0;
  b = 0;
  #500ns;
  rst = 0;
  a = 14;
  b = 161;
  while(test_id<NUM_TESTS) begin
  @(posedge done)
    test_id++;
  expected_val = gcd_fcn_while(a,b);
  if(expected_val==gcd) begin
       $display("[%4d]-GCD(%4d,%4d): expected=%4d   actual=%4d  PASS", test_id, a, b, expected_val, gcd); 
  end else begin
       $display("[%4d]-GCD(%4d,%4d): expected=%4d   actual=%4d  FAIL", test_id, a, b, expected_val, gcd);
  end
  #50ns;
  a = $urandom_range(1000,10);
  b = $urandom_range(1000,10);
  end
  $finish();
end 

initial begin
  $dumpfile("gcd_normal.vcd");
  $dumpvars(1);
end

initial begin
  #600ms;
$finish();
end

endmodule

Labs/Lab1/GCD/gcd_normal.vcd
$date
	Thu Jul 20 01:07:17 2017
$end
$version
	Icarus Verilog
$end
$timescale
	1ps
$end
$scope module GCDTest $end
$var wire 32 ! gcd [31:0] $end
$var wire 1 " done $end
$var reg 32 # a [31:0] $end
$var reg 32 $ b [31:0] $end
$var reg 1 % clk $end
$var reg 1 & rst $end
$upscope $end
$enddefinitions $end
#0
$dumpvars
1&
0%
b0 $
b0 #
x"
b0 !
$end
#50000
0"
1%
#100000
0%
#150000
1%
#200000
0%
#250000
1%
#300000
0%
#350000
1%
#400000
0%
#450000
1%
#500000
0%
b10100001 $
b1110 #
0&
#550000
1%
#600000
0%
#650000
1%
#700000
0%
#750000
1%
#800000
0%
#850000
1%
#900000
0%
#950000
1%
#1000000
0%
#1050000
1%
#1100000
0%
#1150000
1%
#1200000
0%
#1250000
1%
#1300000
0%
#1350000
1%
#1400000
0%
#1450000
1%
#1500000
0%
#1550000
1%
#1600000
0%
#1650000
1%
#1700000
0%
#1750000
1%
#1800000
0%
#1850000
1"
b111 !
1%
#1900000
b111 !
b100000011 $
b1000111111 #
0%
#1950000
0"
b0 !
1%
#2000000
0%
#2050000
1%
#2100000
0%
#2150000
1%
#2200000
0%
#2250000
1%
#2300000
0%
#2350000
1%
#2400000
0%
#2450000
1%
#2500000
0%
#2550000
1%
#2600000
0%
#2650000
1%
#2700000
0%
#2750000
1%
#2800000
0%
#2850000
1%
#2900000
0%
#2950000
1%
#3000000
0%
#3050000
1%
#3100000
0%
#3150000
1%
#3200000
0%
#3250000
1%
#3300000
0%
#3350000
1%
#3400000
0%
#3450000
1%
#3500000
0%
#3550000
1%
#3600000
0%
#3650000
1%
#3700000
0%
#3750000
1%
#3800000
0%
#3850000
1"
b1 !
1%
#3900000
b1 !
b11001011 $
b11011 #
0%
#3950000
0"
b0 !
1%
